odoo/addons/website_event_share/README.rst
odoo/addons/website_event_share/__init__.py
odoo/addons/website_event_share/__manifest__.py
odoo/addons/website_event_share/i18n/it.po
odoo/addons/website_event_share/i18n/website_event_share.pot
odoo/addons/website_event_share/readme/CONTRIBUTORS.rst
odoo/addons/website_event_share/readme/DESCRIPTION.rst
odoo/addons/website_event_share/readme/USAGE.rst
odoo/addons/website_event_share/static/description/icon.png
odoo/addons/website_event_share/static/description/index.html
odoo/addons/website_event_share/static/description/website_event_share.png
odoo/addons/website_event_share/views/website_event.xml
odoo12_addon_website_event_share-12.0.1.0.0.99.dev6.dist-info/METADATA
odoo12_addon_website_event_share-12.0.1.0.0.99.dev6.dist-info/WHEEL
odoo12_addon_website_event_share-12.0.1.0.0.99.dev6.dist-info/top_level.txt
odoo12_addon_website_event_share-12.0.1.0.0.99.dev6.dist-info/RECORD
